pylifttk/__init__.py
pylifttk/normalizations.py
pylifttk/policy.py
pylifttk/util.py
pylifttk/version.py
pylifttk/codepost/__init__.py
pylifttk/codepost/macros.py
pylifttk/csstaff/__init__.py
pylifttk/csstaff/api.py
pylifttk/csstaff/exceptions.py
pylifttk/csstaff/macros.py
pylifttk/csstaff/models.py
pylifttk/csstaff/util.py
pylifttk/ed/__init__.py
pylifttk/ed/api.py
pylifttk/ed/exceptions.py
pylifttk/ed/macros.py
pylifttk/gradescope/__init__.py
pylifttk/gradescope/api.py
pylifttk/gradescope/exceptions.py
pylifttk/gradescope/macros.py
pylifttk/gradescope/util.py
pylifttk/integrations/__init__.py
pylifttk/integrations/codepost_test_transfer.py
pylifttk/integrations/final_grades.py
pylifttk/integrations/grading_tests.py
pylifttk/integrations/lateness.py
pylifttk/integrations/roster_sync.py
pylifttk/integrations/ungraded.py
pylifttk/labqueue/__init__.py
pylifttk/legacy/__init__.py
pylifttk/legacy/runscript_extensions.py
pylifttk/runscript/__init__.py
pylifttk/runscript/parser.py
pylifttk/tigerfile/__init__.py
pylifttk/tigerfile/api.py
pylifttk/tigerfile/exceptions.py
pylifttk/tigerfile/macros.py
pylifttk/tigerfile/util.py
pylifttk-0.0.38.dist-info/LICENSE
pylifttk-0.0.38.dist-info/METADATA
pylifttk-0.0.38.dist-info/WHEEL
pylifttk-0.0.38.dist-info/top_level.txt
pylifttk-0.0.38.dist-info/RECORD
