Metadata-Version: 2.1
Name: pylifttk
Version: 0.0.38
Summary: Python utility toolkit for Princeton CS's LIFT.
Home-page: https://github.com/jlumbroso/pylifttk
Author: Jérémie Lumbroso
Author-email: lumbroso@cs.princeton.edu
License: MIT
Platform: UNKNOWN
Classifier: License :: OSI Approved :: MIT License
Classifier: Programming Language :: Python :: 3
Classifier: Programming Language :: Python :: 3.7
Requires-Dist: bs4
Requires-Dist: codepost
Requires-Dist: confuse
Requires-Dist: python-dateutil
Requires-Dist: pywsse
Requires-Dist: PyYAML
Requires-Dist: requests
Requires-Dist: six
